[
  {
    "titulo": "Announcing Angular v20",
    "texto": "The past couple of years have been transformative for Angular, as we’ve unleashed major advancements like reactivity with Signals and the…",
    "autor": {
      "autornombre": "Minko Gechev"
    },
    "fecha": "May 28",
    "reacciones": {
      "likes": "2.6K",
      "comentarios": "31"
    }
  },
  {
    "titulo": "Build AI-Powered Apps With Genkit and Angular",
    "texto": "There has never been a better time to start building with AI and the state-of-the-art models available to developers everywhere. Building…",
    "autor": {
      "autornombre": "Angular"
    },
    "fecha": "Mar 17",
    "reacciones": {
      "likes": "225",
      "comentarios": "6"
    }
  },
  {
    "titulo": "Seamless data fetching with httpResource",
    "texto": "Fantastic new APIs are coming to Angular. Two years ago, we proposed making Angular a reactive web framework powered by signals. Since…",
    "autor": {
      "autornombre": "Matthieu Riegler"
    },
    "fecha": "Mar 7",
    "reacciones": {
      "likes": "548",
      "comentarios": "8"
    }
  },
  {
    "titulo": "Angular 19.2 Is Now Available",
    "texto": "And we’re back with Angular’s latest minor release, version 19.2, bringing new APIs and experimental features to empower developers on…",
    "autor": {
      "autornombre": "Angular"
    },
    "fecha": "Mar 5",
    "reacciones": {
      "likes": "584",
      "comentarios": "12"
    }
  },
  {
    "titulo": "Micro Frontends with Angular and Native Federation",
    "texto": "Enterprise-scale software systems are often implemented by several cross-functional teams. To enable such teams to provide new features…",
    "autor": {
      "autornombre": "Manfred Steyer"
    },
    "fecha": "Feb 10",
    "reacciones": {
      "likes": "659",
      "comentarios": "11"
    }
  },
  {
    "titulo": "Angular 2025 Strategy",
    "texto": "For the past two and a half years, we’ve been laser focused on improving developer experience and performance for all Angular developers…",
    "autor": {
      "autornombre": "Minko Gechev"
    },
    "fecha": "Jan 13",
    "reacciones": {
      "likes": "1.4K",
      "comentarios": "26"
    }
  },
  {
    "titulo": "Try Out the New Signal Input Migrations",
    "texto": "Authors: Paul Gschwendtner Mark Thompson",
    "autor": {
      "autornombre": "Angular"
    },
    "fecha": "Jan 9",
    "reacciones": {
      "likes": "359",
      "comentarios": "3"
    }
  },
  {
    "titulo": "Meet Angular v19",
    "texto": "In the past two years we doubled down on our investment in developer experience and performance — in every single release we’ve been…",
    "autor": {
      "autornombre": "Minko Gechev"
    },
    "fecha": "Nov 19, 2024",
    "reacciones": {
      "likes": "3.7K",
      "comentarios": "59"
    }
  },
  {
    "titulo": "Angular v19 Release: Join the Watch Parties!",
    "texto": "The Angular v19 release is just around the corner, and developers around the world are gearing up to celebrate.",
    "autor": {
      "autornombre": "Angular"
    },
    "fecha": "Nov 14, 2024",
    "reacciones": {
      "likes": "266",
      "comentarios": "3"
    }
  },
  {
    "titulo": "Latest updates to effect() in Angular",
    "texto": "Authors: Alex Rickabaugh Mark Thompson",
    "autor": {
      "autornombre": "Angular"
    },
    "fecha": "Oct 7, 2024",
    "reacciones": {
      "likes": "640",
      "comentarios": "1"
    }
  }
]